ratlog/__init__.py
ratlog-0.1.1.dist-info/METADATA
ratlog-0.1.1.dist-info/RECORD
ratlog-0.1.1.dist-info/WHEEL
ratlog-0.1.1.dist-info/top_level.txt
