Metadata-Version: 2.1
Name: ratlog
Version: 0.1.1
Summary: :rat: Ratlog Python library - Application Logging for Rats, Humans and Machines
Home-page: https://github.com/alxwrd/ratlog.py
Author: Alex Ward
Author-email: alxwrd@googlemail.com
License: UNKNOWN
Project-URL: Source, https://github.com/alxwrd/ratlog.py
Project-URL: Bug Reports, https://github.com/alxwrd/ratlog.py/issues
Keywords: logging logger logs logging-library ratlog rats python-logger python-logging
Platform: UNKNOWN
Classifier: License :: OSI Approved :: MIT License
Classifier: Programming Language :: Python :: 2
Classifier: Programming Language :: Python :: 2.7
Classifier: Programming Language :: Python :: 3
Classifier: Programming Language :: Python :: 3.4
Classifier: Programming Language :: Python :: 3.5
Classifier: Programming Language :: Python :: 3.6
Requires-Python: >=2.7, !=3.0.*, !=3.1.*, !=3.2.*, <4
